LICENSE.txt
MANIFEST.in
README.rst
pyproject.toml
setup.py
pmipyvips.egg-info/PKG-INFO
pmipyvips.egg-info/SOURCES.txt
pmipyvips.egg-info/dependency_links.txt
pmipyvips.egg-info/not-zip-safe
pmipyvips.egg-info/requires.txt
pmipyvips.egg-info/top_level.txt
pyvips/__init__.py
pyvips/base.py
pyvips/enums.py
pyvips/error.py
pyvips/gobject.py
pyvips/gvalue.py
pyvips/pyvips_build.py
pyvips/vconnection.py
pyvips/vdecls.py
pyvips/version.py
pyvips/vimage.py
pyvips/vinterpolate.py
pyvips/vobject.py
pyvips/voperation.py
pyvips/vregion.py
pyvips/vsource.py
pyvips/vsourcecustom.py
pyvips/vtarget.py
pyvips/vtargetcustom.py
tests/test_block.py
tests/test_connections.py
tests/test_constants.py
tests/test_gvalue.py
tests/test_image.py
tests/test_progress.py
tests/test_saveload.py