Metadata-Version: 2.4
Name: pmipyvips
Version: 3.0.0
Summary: binding for the libvips image processing library
Author-email: John Cupitt <jcupitt@gmail.com>
License: MIT
Project-URL: changelog, https://github.com/boussaffawalid/pyvips/blob/master/CHANGELOG.rst
Project-URL: documentation, https://libvips.github.io/pyvips/
Project-URL: funding, https://opencollective.com/libvips
Project-URL: homepage, https://github.com/boussaffawalid/pyvips
Project-URL: issues, https://github.com/boussaffawalid/pyvips/issues
Project-URL: source, https://github.com/boussaffawalid/pyvips
Keywords: image processing
Classifier: Development Status :: 5 - Production/Stable
Classifier: Environment :: Console
Classifier: Intended Audience :: Developers
Classifier: Intended Audience :: Science/Research
Classifier: Topic :: Multimedia :: Graphics
Classifier: Topic :: Multimedia :: Graphics :: Graphics Conversion
Classifier: License :: OSI Approved :: MIT License
Classifier: Programming Language :: Python
Classifier: Programming Language :: Python :: 3
Classifier: Programming Language :: Python :: 3 :: Only
Classifier: Programming Language :: Python :: 3.7
Classifier: Programming Language :: Python :: 3.8
Classifier: Programming Language :: Python :: 3.9
Classifier: Programming Language :: Python :: 3.10
Classifier: Programming Language :: Python :: 3.11
Classifier: Programming Language :: Python :: 3.12
Classifier: Programming Language :: Python :: 3.13
Classifier: Programming Language :: Python :: Implementation :: CPython
Classifier: Programming Language :: Python :: Implementation :: PyPy
Requires-Python: >=3.7
License-File: LICENSE.txt
Requires-Dist: cffi>=1.0.0
Provides-Extra: binary
Requires-Dist: pyvips-binary; extra == "binary"
Provides-Extra: tox
Requires-Dist: tox; extra == "tox"
Provides-Extra: test
Requires-Dist: pytest; extra == "test"
Requires-Dist: pyperf; extra == "test"
Provides-Extra: sdist
Requires-Dist: build; extra == "sdist"
Provides-Extra: doc
Requires-Dist: sphinx; extra == "doc"
Requires-Dist: sphinx_rtd_theme; extra == "doc"
Dynamic: license-file
